Workbook

Sheet 1. Supply & Vesting
A1: SATOSHI STOP LOSS | Token Supply & Vesting
A2: Total Supply: 1,000,000,000 SSL | Seed: $1.5M at $15M FDV ($0.015/token) | All figures in SSL tokens unless noted
A4: A. Token Allocation
A5: Bucket | B5: Alloc % | C5: SSL Tokens | D5: Cliff (mo) | E5: Vest (mo) | F5: TGE Unlock | G5: TGE Tokens | H5: Notes
A6: Team & Founders | B6: 0.18 | C6: 180000000 | D6: 12 | E6: 48 | F6: — | G6: — | H6: Monthly linear after 12-mo cliff
A7: Seed Investors | B7: 0.1 | C7: 100000000 | D7: 6 | E7: 24 | F7: — | G7: — | H7: $0.015/token · $1.5M raised · 2× lead valuation target $30M+
A8: IF Bootstrap Reserve | B8: 0.22 | C8: 220000000 | D8: — | E8: 48 | F8: — | G8: — | H8: Distributed monthly to early IF underwriters; aligns stakers with protocol growth
A9: Protocol Treasury | B9: 0.15 | C9: 150000000 | D9: 3 | E9: 48 | F9: — | G9: — | H9: Governance-controlled; 3-mo cliff then 45-mo linear
A10: Community & Airdrop | B10: 0.08 | C10: 80000000 | D10: — | E10: 12 | F10: 0.2 | G10: 16000000 | H10: 20% at TGE; 12-mo linear for remainder
A11: DEX Liquidity | B11: 0.05 | C11: 50000000 | D11: — | E11: — | F11: 1 | G11: 50000000 | H11: 100% at TGE to seed protocol liquidity pools
A12: Advisors | B12: 0.04 | C12: 40000000 | D12: 6 | E12: 24 | F12: — | G12: — | H12: Monthly linear after 6-mo cliff
A13: Auctioneer Incentives | B13: 0.03 | C13: 30000000 | D13: — | E13: 24 | F13: — | G13: — | H13: Performance-based release over 24 months
A14: Future Financing Reserve | B14: 0.15 | C14: 150000000 | D14: — | E14: — | F14: — | G14: — | H14: Locked; governance supermajority required to release (Series A, ecosystem expansion)
A15: TOTAL | B15: =SUM(B6:B14) -> 1 | C15: =SUM(C6:C14) -> 1000000000 | G15: =SUM(G6:G14) -> 66000000 | H15: TGE float: 6.6% of total supply
A17: B. Circulating Supply — Monthly (60-Month View)
A18: Month | B18: Year | C18: Team | D18: Seed Inv. | E18: IF Bootstrap | F18: Treasury | G18: Community | H18: DEX Liq. | I18: Advisors | J18: Auctioneers | K18: TOTAL Circ. | L18: % of Supply
A19: 1 | B19: 1 | C19: 0 | D19: 0 | E19: 4583333 | F19: 0 | G19: 16000000 | H19: 50000000 | I19: 0 | J19: 1250000 | K19: 71833333 | L19: 0.071833333
A20: 2 | B20: 1 | C20: 0 | D20: 0 | E20: 9166667 | F20: 0 | G20: 21333333 | H20: 50000000 | I20: 0 | J20: 2500000 | K20: 83000000 | L20: 0.083
A21: 3 | B21: 1 | C21: 0 | D21: 0 | E21: 13750000 | F21: 0 | G21: 26666667 | H21: 50000000 | I21: 0 | J21: 3750000 | K21: 94166667 | L21: 0.094166667
A22: 4 | B22: 1 | C22: 0 | D22: 0 | E22: 18333333 | F22: 3333333 | G22: 32000000 | H22: 50000000 | I22: 0 | J22: 5000000 | K22: 108666667 | L22: 0.10866667
A23: 5 | B23: 1 | C23: 0 | D23: 0 | E23: 22916667 | F23: 6666667 | G23: 37333333 | H23: 50000000 | I23: 0 | J23: 6250000 | K23: 123166667 | L23: 0.12316667
A24: 6 | B24: 1 | C24: 0 | D24: 0 | E24: 27500000 | F24: 10000000 | G24: 42666667 | H24: 50000000 | I24: 0 | J24: 7500000 | K24: 137666667 | L24: 0.13766667
A25: 7 | B25: 1 | C25: 0 | D25: 4166667 | E25: 32083333 | F25: 13333333 | G25: 48000000 | H25: 50000000 | I25: 1666667 | J25: 8750000 | K25: 158000000 | L25: 0.158
A26: 8 | B26: 1 | C26: 0 | D26: 8333333 | E26: 36666667 | F26: 16666667 | G26: 53333333 | H26: 50000000 | I26: 3333333 | J26: 10000000 | K26: 178333333 | L26: 0.17833333
A27: 9 | B27: 1 | C27: 0 | D27: 12500000 | E27: 41250000 | F27: 20000000 | G27: 58666667 | H27: 50000000 | I27: 5000000 | J27: 11250000 | K27: 198666667 | L27: 0.19866667
A28: 10 | B28: 1 | C28: 0 | D28: 16666667 | E28: 45833333 | F28: 23333333 | G28: 64000000 | H28: 50000000 | I28: 6666667 | J28: 12500000 | K28: 219000000 | L28: 0.219
A29: 11 | B29: 1 | C29: 0 | D29: 20833333 | E29: 50416667 | F29: 26666667 | G29: 69333333 | H29: 50000000 | I29: 8333333 | J29: 13750000 | K29: 239333333 | L29: 0.23933333
A30: 12 | B30: 1 | C30: 0 | D30: 25000000 | E30: 55000000 | F30: 30000000 | G30: 74666667 | H30: 50000000 | I30: 10000000 | J30: 15000000 | K30: 259666667 | L30: 0.25966667
... A78: 60 | B78: 5 | C78: 180000000 | D78: 100000000 | E78: 220000000 | F78: 150000000 | G78: 80000000 | H78: 50000000 | I78: 40000000 | J78: 30000000 | K78: 850000000 | L78: 0.85
A80: C. Key Unlock Events Calendar
A81: Month | B81: Est. Date | C81: Event | D81: Tokens Released | E81: Bucket | F81: % Supply
A82: 1 | B82: Jan 2027 | C82: TGE — DEX liquidity + community airdrop tranche | D82: 66000000 | E82: DEX + Community | F82: 0.066
A83: 6 | B83: Jun 2027 | C83: Seed investor cliff lifts — first monthly tranche | D83: 4166667 | E83: Seed Investors | F83: 0.004
A84: 7 | B84: Jul 2027 | C84: Advisor cliff lifts — first monthly tranche | D84: 1666667 | E84: Advisors | F84: 0.002
A85: 12 | B85: Jan 2028 | C85: Team cliff lifts — first monthly tranche (12-mo cliff done) | D85: 3750000 | E85: Team | F85: 0.004
A86: 24 | B86: Jan 2029 | C86: Seed investors fully vested (18 months post-cliff) | D86: 100000000 | E86: Seed Investors | F86: 0.1
A87: 30 | B87: Jul 2029 | C87: Advisors fully vested; IF Bootstrap ~62% released | D87: 220000000 | E87: Multiple | F87: 0.22
A88: 48 | B88: Jan 2031 | C88: Team fully vested; IF Bootstrap 100% released | D88: 180000000 | E88: Team + IF Boot. | F88: 0.18
A89: 60 | B89: Jan 2032 | C89: 60-month: 85% circulating; Future Reserve still locked | D89: 850000000 | E89: All scheduled | F89: 0.85
A91: Note: IF Bootstrap Reserve released monthly to active IF underwriters — not a linear vesting schedule. Future Financing Reserve (150M / 15%) requires governance supermajority to release.

Sheet 2. IF Underwriting
A1: SATOSHI STOP LOSS | Insurance Fund Underwriting Model
A2: IF stakers = underwriters + insurance holders. Yield = cash return from premiums. Protection = enrolled position value. Blue cells = inputs.
A4: A. Core Protocol Parameters
A5: Parameter | B5: Value | C5: Unit | D5: Notes
A6: Enrollment Premium Rate | B6: 0.005 | C6: one-time | D6: 0.5% on vault creation — paid once per enrollment or re-enrollment
A7: Ongoing Fee Rate (annual) | B7: 0.001 | C7: %/yr | D7: 10 bps/year on enrolled AUM; accrued and charged quarterly
A8: AUM Renewal / Re-enroll Rate | B8: 0.3 | C8: %/yr | D8: 30% of AUM re-enrolls each year (pays enrollment premium again)
A9: Auctioneer Volume / AUM (on trigger) | B9: 0.02 | C9: ×AUM | D9: % of AUM clearing through auctioneer network if trigger fires
A10: SSL Revenue Share — Auctioneer Gross | B10: 0.1 | C10: % | D10: Protocol keeps 10% of auctioneer gross spread at trigger
A11: Annual Trigger Probability | B11: 0.02 | C11: %/yr | D11: 2% baseline; implies avg ~50-year interval before Satoshi moves
A12: Staker Share — Enrollment Premiums | B12: 0.5 | C12: % | D12: 50% to stakers; 50% retained to grow IF capital base
A13: Staker Share — Ongoing Fees | B13: 0.5 | C13: % | D13: 50% to stakers; 50% retained to grow IF capital base
A14: Staking Participation Rate | B14: 0.45 | C14: % circ. | D14: 45% of circulating supply staked; typical DeFi protocol range
A15: BTC Price (current) | B15: 67000 | C15: USD | D15: Source: Market data April 2026 — update as needed
A16: SSL Token Price — Seed | B16: 0.015 | C16: USD | D16: Seed round entry price: $1.5M raised at $15M FDV
A17: Satoshi Holdings (est.) | B17: =B15*1100000 -> 73700000000 | C17: USD | D17: ~1.1M BTC at known Patoshi pattern addresses × current BTC price
A18: Seed FDV | B18: =1000000000*B16 -> 15000000 | C18: USD | D18: 1B total supply × seed token price
A19: Capital Raised (Seed) | B19: =0.1*1000000000*B16 -> 1500000 | C19: USD | D19: 10% of supply to seed investors at seed token price
A21: B. AUM Growth Scenarios — Enrolled USD Value
A22: Scenario | B22: Year 1 | C22: Year 2 | D22: Year 3 | E22: Year 4 | F22: Year 5 | G22: Rationale
A23: Bear | B23: 50000000 | C23: 120000000 | D23: 250000000 | E23: 400000000 | F23: 600000000 | G23: Slow adoption; limited chain coverage; no trigger event in period
A24: Base | B24: 200000000 | C24: 500000000 | D24: 1000000000 | E24: 1800000000 | F24: 3000000000 | G24: Moderate growth; 2 chains live Y1; ~0.3% of wBTC+cbBTC TAM by Y3
A25: Bull | B25: 500000000 | C25: 1500000000 | D25: 3500000000 | E25: 7000000000 | F25: 12000000000 | G25: Rapid adoption; major exchange partnerships; trigger near-miss boosts demand
A27: C. Annual Staker Cash Yield — by Scenario and Year
A28: Metric | B28: Scenario | C28: Year 1 | D28: Year 2 | E28: Year 3 | F28: Year 4 | G28: Year 5
A29: Enrollment Revenue → Stakers | B29: Bear | C29: ='2. IF Underwriting'!B23*B6*B8*B12 -> 37500 | D29: ='2. IF Underwriting'!C23*B6*B8*B12 -> 90000 | E29: ='2. IF Underwriting'!D23*B6*B8*B12 -> 187500 | F29: ='2. IF Underwriting'!E23*B6*B8*B12 -> 300000 | G29: ='2. IF Underwriting'!F23*B6*B8*B12 -> 450000
A30: Ongoing Fee Revenue → Stakers | B30: Bear | C30: ='2. IF Underwriting'!B23*B7*B13 -> 25000 | D30: ='2. IF Underwriting'!C23*B7*B13 -> 60000 | E30: ='2. IF Underwriting'!D23*B7*B13 -> 125000 | F30: ='2. IF Underwriting'!E23*B7*B13 -> 200000 | G30: ='2. IF Underwriting'!F23*B7*B13 -> 300000
A31: Auctioneer Rev. → Stakers (EV)* | B31: Bear | C31: ='2. IF Underwriting'!B23*B11*B9*B10 -> 2000 | D31: ='2. IF Underwriting'!C23*B11*B9*B10 -> 4800 | E31: ='2. IF Underwriting'!D23*B11*B9*B10 -> 10000 | F31: ='2. IF Underwriting'!E23*B11*B9*B10 -> 16000 | G31: ='2. IF Underwriting'!F23*B11*B9*B10 -> 24000
A32: TOTAL Cash Yield to Stakers | B32: Bear | C32: =C29+C30+C31 -> 64500 | D32: =D29+D30+D31 -> 154800 | E32: =E29+E30+E31 -> 322500 | F32: =F29+F30+F31 -> 516000 | G32: =G29+G30+G31 -> 774000
A33: Staked Capital (USD: staked supply × token price) | B33: Bear | C33: 7200000 | D33: 17010000 | E33: 31275000 | F33: 42660000 | G33: 57375000
A34: Cash APY (staker yield / staked capital) | B34: Bear | C34: =IFERROR(C32/C33,0) -> 0.0089583333 | D34: =IFERROR(D32/D33,0) -> 0.0091005291 | E34: =IFERROR(E32/E33,0) -> 0.010311751 | F34: =IFERROR(F32/F33,0) -> 0.01209564 | G34: =IFERROR(G32/G33,0) -> 0.013490196
A35: Token Price Assumption | B35: Bear | C35: 0.05 | D35: 0.07 | E35: 0.1 | F35: 0.12 | G35: 0.15
A37: Enrollment Revenue → Stakers | B37: Base | C37: ='2. IF Underwriting'!B24*B6*B8*B12 -> 150000 | D37: ='2. IF Underwriting'!C24*B6*B8*B12 -> 375000 | E37: ='2. IF Underwriting'!D24*B6*B8*B12 -> 750000 | F37: ='2. IF Underwriting'!E24*B6*B8*B12 -> 1350000 | G37: ='2. IF Underwriting'!F24*B6*B8*B12 -> 2250000
A38: Ongoing Fee Revenue → Stakers | B38: Base | C38: ='2. IF Underwriting'!B24*B7*B13 -> 100000 | D38: ='2. IF Underwriting'!C24*B7*B13 -> 250000 | E38: ='2. IF Underwriting'!D24*B7*B13 -> 500000 | F38: ='2. IF Underwriting'!E24*B7*B13 -> 900000 | G38: ='2. IF Underwriting'!F24*B7*B13 -> 1500000
A39: Auctioneer Rev. → Stakers (EV)* | B39: Base | C39: ='2. IF Underwriting'!B24*B11*B9*B10 -> 8000 | D39: ='2. IF Underwriting'!C24*B11*B9*B10 -> 20000 | E39: ='2. IF Underwriting'!D24*B11*B9*B10 -> 40000 | F39: ='2. IF Underwriting'!E24*B11*B9*B10 -> 72000 | G39: ='2. IF Underwriting'!F24*B11*B9*B10 -> 120000
A40: TOTAL Cash Yield to Stakers | B40: Base | C40: =C37+C38+C39 -> 258000 | D40: =D37+D38+D39 -> 645000 | E40: =E37+E38+E39 -> 1290000 | F40: =F37+F38+F39 -> 2322000 | G40: =G37+G38+G39 -> 3870000
A41: Staked Capital (USD: staked supply × token price) | B41: Base | C41: 14400000 | D41: 48600000 | E41: 125100000 | F41: 248850000 | G41: 420750000
A42: Cash APY (staker yield / staked capital) | B42: Base | C42: =IFERROR(C40/C41,0) -> 0.017916667 | D42: =IFERROR(D40/D41,0) -> 0.013271605 | E42: =IFERROR(E40/E41,0) -> 0.010311751 | F42: =IFERROR(F40/F41,0) -> 0.0093309222 | G42: =IFERROR(G40/G41,0) -> 0.009197861
A43: Token Price Assumption | B43: Base | C43: 0.1 | D43: 0.2 | E43: 0.4 | F43: 0.7 | G43: 1.1
A45: Enrollment Revenue → Stakers | B45: Bull | C45: ='2. IF Underwriting'!B25*B6*B8*B12 -> 375000 | D45: ='2. IF Underwriting'!C25*B6*B8*B12 -> 1125000 | E45: ='2. IF Underwriting'!D25*B6*B8*B12 -> 2625000 | F45: ='2. IF Underwriting'!E25*B6*B8*B12 -> 5250000 | G45: ='2. IF Underwriting'!F25*B6*B8*B12 -> 9000000
A46: Ongoing Fee Revenue → Stakers | B46: Bull | C46: ='2. IF Underwriting'!B25*B7*B13 -> 250000 | D46: ='2. IF Underwriting'!C25*B7*B13 -> 750000 | E46: ='2. IF Underwriting'!D25*B7*B13 -> 1750000 | F46: ='2. IF Underwriting'!E25*B7*B13 -> 3500000 | G46: ='2. IF Underwriting'!F25*B7*B13 -> 6000000
A47: Auctioneer Rev. → Stakers (EV)* | B47: Bull | C47: ='2. IF Underwriting'!B25*B11*B9*B10 -> 20000 | D47: ='2. IF Underwriting'!C25*B11*B9*B10 -> 60000 | E47: ='2. IF Underwriting'!D25*B11*B9*B10 -> 140000 | F47: ='2. IF Underwriting'!E25*B11*B9*B10 -> 280000 | G47: ='2. IF Underwriting'!F25*B11*B9*B10 -> 480000
A48: TOTAL Cash Yield to Stakers | B48: Bull | C48: =C45+C46+C47 -> 645000 | D48: =D45+D46+D47 -> 1935000 | E48: =E45+E46+E47 -> 4515000 | F48: =F45+F46+F47 -> 9030000 | G48: =G45+G46+G47 -> 15480000
A49: Staked Capital (USD: staked supply × token price) | B49: Bull | C49: 28800000 | D49: 145800000 | E49: 469125000 | F49: 1066500000 | G49: 2103750000
A50: Cash APY (staker yield / staked capital) | B50: Bull | C50: =IFERROR(C48/C49,0) -> 0.022395833 | D50: =IFERROR(D48/D49,0) -> 0.013271605 | E50: =IFERROR(E48/E49,0) -> 0.0096243006 | F50: =IFERROR(F48/F49,0) -> 0.008466948 | G50: =IFERROR(G48/G49,0) -> 0.0073582888
A51: Token Price Assumption | B51: Bull | C51: 0.2 | D51: 0.6 | E51: 1.5 | F51: 3 | G51: 5.5
A53: * Auctioneer revenue uses expected value: trigger probability × auctioneer volume × SSL share. Actual revenue = 0 in non-trigger years; potentially large in trigger year.
A55: D. Integrated Participant Analysis — Staker Who Also Enrolls
A56: Key insight: An IF staker who also enrolls their own crypto position receives BOTH cash yield (from staking) AND protection value (as an enrollee). Their net cost of protection may approach zero or turn positive at scale.
A58: Metric | B58: Value | C58: Unit | D58: Notes
A59: Participant's enrolled position size | B59: 100000 | C59: USD | D59: Change this to model different position sizes
A60: SSL staked (USD value) | B60: 100000 | C60: USD | D60: Equal stake and position size is illustrative; can differ
A61: Annual enrollment cost (amortized) | B61: =B59*B6 -> 500 | C61: USD/yr | D61: One-time premium / first year; 0 in renewal years (already paid)
A62: Annual ongoing fee cost | B62: =B59*B7 -> 100 | C62: USD/yr | D62: 10 bps/year on enrolled position
A63: Total protection cost (Year 1) | B63: =B61+B62 -> 600 | C63: USD/yr | D63: Year 1 total; Year 2+ = ongoing fee only ($100 on $100K)
A65: Staking Yield at AUM Scale (Base Scenario) | B65: $200M AUM | C65: $500M AUM | D65: $1B AUM | E65: $1.8B AUM | F65: $3B AUM | G65: Unit
A66: Total protocol revenue to stakers | B66: =200000000*(B6*B8+B7)*B12 -> 250000 | C66: =500000000*(B6*B8+B7)*B12 -> 625000 | D66: =1000000000*(B6*B8+B7)*B12 -> 1250000 | E66: =1800000000*(B6*B8+B7)*B12 -> 2250000 | F66: =3000000000*(B6*B8+B7)*B12 -> 3750000 | G66: USD/yr
A67: Yield on $100K staked (at base APYs) | B67: =B60*0.011 -> 1100 | C67: =B60*0.019 -> 1900 | D67: =B60*0.023 -> 2300 | E67: =B60*0.025 -> 2500 | F67: =B60*0.028 -> 2800 | G67: USD/yr
A68: NET: staking yield MINUS protection cost (Year 1) | B68: =B67-B63 -> 500 | C68: =C67-B63 -> 1300 | D68: =D67-B63 -> 1700 | E68: =E67-B63 -> 1900 | F68: =F67-B63 -> 2200 | G68: USD/yr (+ = net earner)
A70: Interpretation: A participant staking $100K of SSL who also enrolls $100K of wBTC earns staking yield that increasingly offsets (and eventually exceeds) their protection cost as protocol AUM grows. At $1B+ AUM they are net earners — effectively paid to hold protection.

Sheet 3. Protocol Revenue
A1: SATOSHI STOP LOSS | Protocol Revenue Projections
A2: Monthly projections (Base scenario, 36 months). Annual Bear / Base / Bull summary.
A4: A. Revenue Assumptions (linked from IF Underwriting model)
A5: Parameter | B5: Value | C5: Unit | D5: Notes
A6: Enrollment Premium Rate | B6: 0.005 | C6: % | D6: Matches IF Underwriting model input
A7: Ongoing Fee (annual) | B7: 0.001 | C7: %/yr | D7: 10 bps/year; accrued monthly
A8: Annual AUM Renewal Rate | B8: 0.3 | C8: %/yr | D8: 30% of AUM re-enrolls per year
A9: Auctioneer Share (IF) | B9: 0.1 | C9: % | D9: 10% of auctioneer gross spread; trigger events only
A10: Annual Trigger Probability | B10: 0.02 | C10: %/yr | D10: 2% expected value basis
A11: Auctioneer Vol / AUM | B11: 0.02 | C11: ×AUM | D11: % of AUM through auctioneer if trigger fires
A12: Staker Revenue Share | B12: 0.5 | C12: % | D12: 50% to stakers; 50% to IF capital
A14: B. Monthly Revenue — Base Scenario (36 Months)
A15: Month | B15: AUM ($) | C15: New AUM | D15: Enrollment Rev | E15: Ongoing Fee Rev | F15: Auctioneer Rev* | G15: Total Revenue | H15: IF Capital | I15: Staker Revenue | J15: Cumul. Revenue
A16: 1 | B16: 8487654.3 | C16: 8487654.3 | D16: 43499.23 | E16: 707.3 | F16: 28.29 | G16: 44234.83 | H16: 22117.41 | I16: 22117.41 | J16: =SUM(G16) -> 44234.83
A17: 2 | B17: 23102720 | C17: 14615066 | D17: 75963.17 | E17: 1925.23 | F17: 77.01 | G17: 77965.41 | H17: 38982.7 | I17: 38982.7 | J17: =SUM(G16:G17) -> 122200.24
A18: 3 | B18: 41168078 | C18: 18065358 | D18: 95472.8 | E18: 3430.67 | F18: 137.23 | G18: 99040.7 | H18: 49520.35 | I18: 49520.35 | J18: =SUM(G16:G18) -> 221240.94
A19: 4 | B19: 61728395 | C19: 20560317 | D19: 110517.63 | E19: 5144.03 | F19: 205.76 | G19: 115867.43 | H19: 57933.71 | I19: 57933.71 | J19: =SUM(G16:G19) -> 337108.37
A20: 5 | B20: 84231542 | C20: 22503147 | D20: 123044.68 | E20: 7019.3 | F20: 280.77 | G20: 130344.75 | H20: 65172.37 | I20: 65172.37 | J20: =SUM(G16:G20) -> 467453.12
A21: 6 | B21: 1.0830499e+08 | C21: 24073444 | D21: 133905.34 | E21: 9025.42 | F21: 361.02 | G21: 143291.77 | H21: 71645.89 | I21: 71645.89 | J21: =SUM(G16:G21) -> 610744.89
A22: 7 | B22: 1.3367524e+08 | C22: 25370254 | D22: 143560.67 | E22: 11139.6 | F22: 445.58 | G22: 155145.86 | H22: 77572.93 | I22: 77572.93 | J22: =SUM(G16:G22) -> 765890.75
A23: 8 | B23: 1.601304e+08 | C23: 26455165 | D23: 152292.13 | E23: 13344.2 | F23: 533.77 | G23: 166170.09 | H23: 83085.05 | I23: 83085.05 | J23: =SUM(G16:G23) -> 932060.84
A24: 9 | B24: 187500000 | C24: 27369596 | D24: 160285.48 | E24: 15625 | F24: 625 | G24: 176535.48 | H24: 88267.74 | I24: 88267.74 | J24: =SUM(G16:G24) -> 1108596.3
A25: 10 | B25: 2.1564299e+08 | C25: 28142993 | D25: 167670.34 | E25: 17970.25 | F25: 718.81 | G25: 186359.4 | H25: 93179.7 | I25: 93179.7 | J25: =SUM(G16:G25) -> 1294955.7
A26: 11 | B26: 2.4444018e+08 | C26: 28797186 | D26: 174540.95 | E26: 20370.01 | F26: 814.8 | G26: 195725.77 | H26: 97862.88 | I26: 97862.88 | J26: =SUM(G16:G26) -> 1490681.5
A27: 12 | B27: 2.7378907e+08 | C27: 29348889 | D27: 180968.08 | E27: 22815.76 | F27: 912.63 | G27: 204696.46 | H27: 102348.23 | I27: 102348.23 | J27: =SUM(G16:G27) -> 1695377.9
A28: 13 | B28: 3.0360031e+08 | C28: 29811240 | D28: 187006.24 | E28: 25300.03 | F28: 1012 | G28: 213318.26 | H28: 106659.13 | I28: 106659.13 | J28: =SUM(G16:G28) -> 1908696.2
A29: 14 | B29: 3.3379509e+08 | C29: 30194786 | D29: 192698.31 | E29: 27816.26 | F29: 1112.65 | G29: 221627.22 | H29: 110813.61 | I29: 110813.61 | J29: =SUM(G16:G29) -> 2130323.4
A30: 15 | B30: 3.6430324e+08 | C30: 30508149 | D30: 198078.65 | E30: 30358.6 | F30: 1214.34 | G30: 229651.6 | H30: 114825.8 | I30: 114825.8 | J30: =SUM(G16:G30) -> 2359975
A31: 16 | B31: 3.9506173e+08 | C31: 30758486 | D31: 203175.15 | E31: 32921.81 | F31: 1316.87 | G31: 237413.83 | H31: 118706.91 | I31: 118706.91 | J31: =SUM(G16:G31) -> 2597388.9
A32: 17 | B32: 4.2601354e+08 | C32: 30951811 | D32: 208010.75 | E32: 35501.13 | F32: 1420.05 | G32: 244931.92 | H32: 122465.96 | I32: 122465.96 | J32: =SUM(G16:G32) -> 2842320.8
A33: 18 | B33: 4.5710678e+08 | C33: 31093241 | D33: 212604.55 | E33: 38092.23 | F33: 1523.69 | G33: 252220.48 | H33: 126110.24 | I33: 126110.24 | J33: =SUM(G16:G33) -> 3094541.3
A34: 19 | B34: 4.8829395e+08 | C34: 31187169 | D34: 216972.59 | E34: 40691.16 | F34: 1627.65 | G34: 259291.4 | H34: 129645.7 | I34: 129645.7 | J34: =SUM(G16:G34) -> 3353832.7
A35: 20 | B35: 5.1953135e+08 | C35: 31237400 | D35: 221128.42 | E35: 43294.28 | F35: 1731.77 | G35: 266154.47 | H35: 133077.23 | I35: 133077.23 | J35: =SUM(G16:G35) -> 3619987.1
A36: 21 | B36: 5.5077861e+08 | C36: 31247258 | D36: 225083.61 | E36: 45898.22 | F36: 1835.93 | G36: 272817.76 | H36: 136408.88 | I36: 136408.88 | J36: =SUM(G16:G36) -> 3892804.9
A37: 22 | B37: 5.8199827e+08 | C37: 31219665 | D37: 228848.11 | E37: 48499.86 | F37: 1939.99 | G37: 279287.96 | H37: 139643.98 | I37: 139643.98 | J37: =SUM(G16:G37) -> 4172092.9
A38: 23 | B38: 6.1315548e+08 | C38: 31157207 | D38: 232430.47 | E38: 51096.29 | F38: 2043.85 | G38: 285570.61 | H38: 142785.3 | I38: 142785.3 | J38: =SUM(G16:G38) -> 4457663.5
A39: 24 | B39: 6.4421766e+08 | C39: 31062185 | D39: 235838.13 | E39: 53684.81 | F39: 2147.39 | G39: 291670.33 | H39: 145835.16 | I39: 145835.16 | J39: =SUM(G16:G39) -> 4749333.8
A40: 25 | B40: 6.7515432e+08 | C40: 30936658 | D40: 239077.58 | E40: 56262.86 | F40: 2250.51 | G40: 297590.95 | H40: 148795.48 | I40: 148795.48 | J40: =SUM(G16:G40) -> 5046924.7
A41: 26 | B41: 7.059368e+08 | C41: 30782475 | D41: 242154.48 | E41: 58828.07 | F41: 2353.12 | G41: 303335.67 | H41: 151667.83 | I41: 151667.83 | J41: =SUM(G16:G41) -> 5350260.4
A42: 27 | B42: 7.3653811e+08 | C42: 30601309 | D42: 245073.81 | E42: 61378.18 | F42: 2455.13 | G42: 308907.11 | H42: 154453.56 | I42: 154453.56 | J42: =SUM(G16:G42) -> 5659167.5
A43: 28 | B43: 7.6693278e+08 | C43: 30394673 | D43: 247839.96 | E43: 63911.06 | F43: 2556.44 | G43: 314307.47 | H43: 157153.73 | I43: 157153.73 | J43: =SUM(G16:G43) -> 5973475
A44: 29 | B44: 7.9709672e+08 | C44: 30163944 | D44: 250456.81 | E44: 66424.73 | F44: 2656.99 | G44: 319538.53 | H44: 159769.26 | I44: 159769.26 | J44: =SUM(G16:G44) -> 6293013.5
A45: 30 | B45: 8.270071e+08 | C45: 29910381 | D45: 252927.79 | E45: 68917.26 | F45: 2756.69 | G45: 324601.74 | H45: 162300.87 | I45: 162300.87 | J45: =SUM(G16:G45) -> 6617615.3
A46: 31 | B46: 8.5664224e+08 | C46: 29635136 | D46: 255255.96 | E46: 71386.85 | F46: 2855.47 | G46: 329498.29 | H46: 164749.14 | I46: 164749.14 | J46: =SUM(G16:G46) -> 6947113.5
A47: 32 | B47: 8.8598151e+08 | C47: 29339266 | D47: 257444.02 | E47: 73831.79 | F47: 2953.27 | G47: 334229.08 | H47: 167114.54 | I47: 167114.54 | J47: =SUM(G16:G47) -> 7281342.6
A48: 33 | B48: 9.1500525e+08 | C48: 29023747 | D48: 259494.39 | E48: 76250.44 | F48: 3050.02 | G48: 338794.85 | H48: 169397.42 | I48: 169397.42 | J48: =SUM(G16:G48) -> 7620137.5
A49: 34 | B49: 9.4369473e+08 | C49: 28689479 | D49: 261409.24 | E49: 78641.23 | F49: 3145.65 | G49: 343196.11 | H49: 171598.06 | I49: 171598.06 | J49: =SUM(G16:G49) -> 7963333.6
A50: 35 | B50: 9.7203203e+08 | C50: 28337296 | D50: 263190.48 | E50: 81002.67 | F50: 3240.11 | G50: 347433.26 | H50: 173716.63 | I50: 173716.63 | J50: =SUM(G16:G50) -> 8310766.8
A51: 36 | B51: 1000000000 | C51: 27967972 | D51: 264839.86 | E51: 83333.33 | F51: 3333.33 | G51: 351506.52 | H51: 175753.26 | I51: 175753.26 | J51: =SUM(G16:G51) -> 8662273.4
A53: * Auctioneer revenue uses expected-value basis (2% trigger probability). Actual year-of-trigger revenue would be ~50× higher. IF capital = 50% of total revenue; Staker revenue = 50%.
A55: C. Annual Revenue Summary — Bear / Base / Bull
A56: Metric | B56: Y1 Bear | C56: Y1 Base | D56: Y1 Bull | E56: Y2 Bear | F56: Y2 Base | G56: Y2 Bull | H56: Y3 Bear | I56: Y3 Base | J56: Y3 Bull
A57: AUM at Year-End ($) | B57: 50000000 | C57: 200000000 | D57: 500000000 | E57: 120000000 | F57: 500000000 | G57: 1500000000 | H57: 250000000 | I57: 1000000000 | J57: 3500000000
A58: Enrollment Rev (new AUM) | B58: 125000 | C58: 500000 | D58: 1250000 | E58: 300000 | F58: 750000 | G58: 2250000 | H58: 325000 | I58: 1000000 | J58: 5000000
A59: Enrollment Rev (renewals) | B59: 25000 | C59: 100000 | D59: 250000 | E59: 62500 | F59: 187500 | G59: 562500 | H59: 100000 | I59: 375000 | J59: 1312500
A60: Ongoing Fee Revenue | B60: 50000 | C60: 200000 | D60: 500000 | E60: 120000 | F60: 500000 | G60: 1500000 | H60: 250000 | I60: 1000000 | J60: 3500000
A61: Auctioneer Revenue (EV) | B61: 2000 | C61: 8000 | D61: 20000 | E61: 4800 | F61: 20000 | G61: 60000 | H61: 10000 | I61: 40000 | J61: 140000
A62: TOTAL Protocol Revenue | B62: 202000 | C62: 808000 | D62: 2020000 | E62: 487300 | F62: 1457500 | G62: 4372500 | H62: 685000 | I62: 2415000 | J62: 9952500
A63: Revenue to Stakers | B63: 101000 | C63: 404000 | D63: 1010000 | E63: 243700 | F63: 728800 | G63: 2186300 | H63: 342500 | I63: 1207500 | J63: 4976300
A64: Revenue to IF Capital | B64: 101000 | C64: 404000 | D64: 1010000 | E64: 243700 | F64: 728800 | G64: 2186300 | H64: 342500 | I64: 1207500 | J64: 4976300

Sheet 4. Kill Switch Scenarios
A1: SATOSHI STOP LOSS | Kill Switch Scenario Analysis
A2: Three distinct protocol outcomes: No Event (base) | Trigger Event (Satoshi sells) | Graceful Shutdown (Satoshi alive, proof-of-life detected)
A4: A. Scenario Definitions
A5: Dimension | B5: Trigger Event | C5: Graceful Shutdown | F5: No Event (Base)
A6: Token impact | B6: SSL token likely crashes with BTC; potential governance vote on protocol future | C6: SSL loses yield stream; trades at pure governance discount; wind-down treasury distribution | F6: SSL accrues value with P/S multiples as protocol revenue grows
A7: B. IF Staker 5-Year Financial Model — Base Protocol Run (No Event)
A8: Assumes Base scenario AUM growth. Staker holds $100K of staked SSL + $100K enrolled position. Token price follows Base appreciation path.
A10: Metric | B10: Year 1 | C10: Year 2 | D10: Year 3 | E10: Year 4 | F10: Year 5 | G10: 5-Yr Total
A11: AUM (Base scenario) | B11: 200000000 | C11: 500000000 | D11: 1000000000 | E11: 1800000000 | F11: 3000000000
A12: Total staker yield (all stakers) | B12: 404000 | C12: 1207000 | D12: 2415000 | E12: 4347000 | F12: 7245000
A13: Staked capital (all, USD) | B13: 14400000 | C13: 40500000 | D13: 100700000 | E13: 200900000 | F13: 374700000
A14: Cash APY | B14: 0.028 | C14: 0.03 | D14: 0.024 | E14: 0.022 | F14: 0.019
A15: Yield on $100K staked | B15: 2800 | C15: 3000 | D15: 2400 | E15: 2200 | F15: 1900 | G15: 12300
A16: Protection cost (ongoing, $100K) | B16: 100 | C16: 100 | D16: 100 | E16: 100 | F16: 100
A17: NET value (yield − protection) | B17: 2700 | C17: 2900 | D17: 2300 | E17: 2100 | F17: 1800 | G17: 11800
A18: Token price (Base) | B18: 0.1 | C18: 0.2 | D18: 0.4 | E18: 0.7 | F18: 1.1
A19: Capital appreciation ($100K stk) | B19: 566667 | C19: 1233333 | D19: 2566667 | E19: 4566667 | F19: 7233333
A22: C. Trigger Event — IF Staker Impact Analysis
A23: Parameter | B23: Bear Trigger | C23: Base Trigger | D23: Bull Trigger | E23: Unit | F23: Notes
A24: Protocol AUM at trigger | B24: 250M | C24: 1,000M | D24: 3,500M | E24: USD | F24: Assumed to trigger in Year 3
A25: BTC price drop (immediate) | B25: 30% | C25: 40% | D25: 50% | E25: % | F25: Historical shock scenarios; larger shock in bull = more forced selling
A26: IF capital at trigger | B26: $750K | C26: $3.1M | D26: $10.5M | E26: USD | F26: Cumulative IF capital accumulated from premiums
A27: IF deployment (BTC support) | B27: $750K | C27: $3.1M | D27: $10.5M | E27: USD | F27: All IF capital deployed to buy BTC post-trigger
A28: Residual AUM through DEX | B28: ~$245M | C28: ~$980M | D28: ~$3.4B | E28: USD | F28: Most positions clear through IF + DEX routing
A29: Auctioneer clearance | B29: ~$5M | C29: ~$20M | D29: ~$70M | E29: USD | F29: Residual illiquid positions; auctioneer Dutch auction
A30: IF depletion ratio | B30: 100% | C30: 100% | D30: 100% | E30: % | F30: IF likely fully depleted on any real trigger; stakers absorb losses
A31: Staker loss (on $100K stake) | B31: $100K | C31: $100K | D31: $100K | E31: USD | F31: Full staked capital at risk; capped at stake amount
A32: Enrolled user protection | B32: Full | C32: Full | D32: Full | F32: Protocol's purpose: enrolled users exit at supported price regardless
A33: Pre-trigger cumulative yield | B33: $5.6K | C33: $12.1K | D33: $35K | E33: USD | F33: Net yield earned by staker prior to trigger event (3-year base)
A34: Net staker P&L (3yr + trig) | B34: ($94.4K) | C34: ($87.9K) | D34: ($65K) | E34: USD | F34: Loss minus prior yield; this is the insurance cost of writing cover
A36: Key point: IF stakers are writing catastrophe insurance. Their loss is bounded (capped at stake). Their role is analogous to Lloyd's Names — taking defined risk for defined premium income. Stakers who also hold enrolled crypto positions have a natural hedge: their staked SSL absorbs losses, but their enrolled position exits safely.
A38: D. Graceful Shutdown — Protocol Wind-Down Economics
A39: Triggered if Satoshi moves ≥100 BTC AND cryptographic proof-of-life is verified within 6 hours. Protocol assumes Satoshi is alive and voluntarily managing holdings. SSL enters graceful wind-down.
A41: Wind-Down Metric | B41: Year 1 Shutdown | C41: Year 2 Shutdown | D41: Year 3 Shutdown | E41: Year 5 Shutdown | F41: Notes
A42: Protocol AUM at shutdown | B42: $200M | C42: $500M | D42: $1,000M | E42: $3,000M | F42: Base scenario AUM at shutdown year
A43: IF capital returned to stakers | B43: $600K | C43: $1,600K | D43: $3,100K | E43: $9,600K | F43: 100% returned; no trigger = no depletion
A44: Staked capital returned (ex IF) | B44: 100% | C44: 100% | D44: 100% | E44: 100% | F44: Stakers receive staked SSL back; IF capital in full
A45: Cumulative yield earned (staker) | B45: $2.8K | C45: $5.8K | D45: $8.2K | E45: $14.5K | F45: Pre-shutdown yield on $100K staked position
A46: Treasury governance distribution | B46: TBD | C46: TBD | D46: TBD | E46: TBD | F46: Governance vote on treasury allocation at shutdown
A47: Token value post-shutdown | B47: Decline | C47: Decline | D47: Decline | E47: Decline | F47: Loses yield stream; retains historical governance value; trades at significant discount
A48: Net staker return (ex tok price) | B48: $2.8K | C48: $5.8K | D48: $8.2K | E48: $14.5K | F48: Cash yield + full capital return; positive in all scenarios
A49: Enrolled user impact | B49: None | C49: None | D49: None | E49: None | F49: Vaults released; users withdraw freely; no forced liquidation
A51: E. Scenario Comparison — 3-Year Staker IRR (on $100K staked + $100K enrolled)
A52: Scenario | B52: Cash Yield (3yr) | C52: Capital Return | D52: Token Appreciation | E52: Enrolled Position | F52: Net 3-yr IRR (approx) | G52: Verdict
A53: No Event (Base) | B53: $8.2K | C53: 100% | D53: +40x seed | E53: Protected, held | F53: ~50%+ (token driven) | G53: Best outcome; protocol proves its value without triggering
A54: Graceful Shutdown (Y3) | B54: $8.2K | C54: 100% | D54: Significant discount | E54: Released freely | F54: Positive but muted | G54: Good outcome; mission accomplished; Satoshi is alive
A55: Trigger Event (Y3) | B55: $8.2K | C55: 0% | D55: Crashes with BTC | E55: Exits at supported price | F55: Deep negative (staker) | G55: Insurance claim paid; staker absorbed the loss they were paid to absorb

Sheet 5. Token Valuation
A1: SATOSHI STOP LOSS | Token Valuation Framework
A2: Comparable analysis · FDV scenario table · Seed return multiples. All valuations in USD.
A4: A. Comparable Protocol Analysis (April 2026)
A5: Protocol | B5: Category | C5: Mkt Cap | D5: FDV | E5: TVL / AUM | F5: P/TVL | G5: Rev (est.) | H5: P/S | I5: SSL Relevance
A6: Nexus Mutual (NXM) | B6: DeFi Insurance | C6: 100000000 | D6: 103000000 | E6: 800000000 | F6: 0.125 | G6: 15000000 | H6: 6.7 | I6: Closest analog: mutual model, capital staking for yield, claim risk
A7: GMX | B7: Perp DEX / Risk | C7: 67000000 | D7: 67000000 | E7: 600000000 | F7: 0.112 | G7: 30000000 | H7: 2.2 | I7: Revenue-generating; risk underwriting; high staker APY model
A8: Synthetix (SNX) | B8: Derivatives | C8: 97000000 | D8: 400000000 | E8: 1200000000 | F8: 0.081 | G8: 20000000 | H8: 4.9 | I8: Staking-based collateral; governance token + staking yield
A9: UMA Protocol | B9: Oracle / Risk | C9: 80000000 | D9: 120000000 | E9: 200000000 | F9: 0.4 | G9: 10000000 | H9: 8 | I9: Oracle infrastructure; tail-risk event model
A10: Risk Harbor | B10: DeFi Insurance | C10: 15000000 | D10: 20000000 | E10: 50000000 | F10: 0.3 | G10: 1000000 | H10: 15 | I10: Direct competitor; smaller scale; cover buying model
A11: InsurAce | B11: DeFi Insurance | C11: 12000000 | D11: 18000000 | E11: 80000000 | F11: 0.15 | G11: 2000000 | H11: 6 | I11: Multi-chain insurance; closest product analog
A12: Sherlock | B12: Audit + Insurance | C12: 8000000 | D12: 10000000 | E12: 40000000 | F12: 0.2 | G12: 3000000 | H12: 2.7 | I12: Hybrid security + insurance; staker capital model
A13: Median / Blended | C13: — | D13: — | E13: — | F13: 0.175 | G13: — | H13: 6 | I13: P/TVL 0.10–0.40×; P/S 4–8× are reasonable SSL comp ranges
A15: B. SSL FDV Scenario Table — Token Price & Investor Returns
A16: FDV Scenario | B16: FDV | C16: Token Price | D16: Circ Mkt Cap* | E16: P/S (Base) | F16: P/TVL (Base) | G16: Seed Return | H16: Implied AUM† | I16: Milestone
A17: Seed (entry) | B17: 15000000 | C17: 0.015 | D17: 6.6%×$15M=$1M | E17: 75 | F17: 0.3 | G17: 1.0× | H17: $50M | I17: Today — pre-launch fundraise
A18: Early market | B18: 30000000 | C18: 0.03 | D18: ~$2M circ | E18: 75 | F18: 0.3 | G18: 2.0× | H18: $100M | I18: First exchange integration live
A19: Protocol fit | B19: 75000000 | C19: 0.075 | D19: ~$5M circ | E19: 75 | F19: 0.3 | G19: 5.0× | H19: $250M | I19: $250M AUM, consistent revenue
A20: Breakout | B20: 150000000 | C20: 0.15 | D20: ~$10M circ | E20: 75 | F20: 0.3 | G20: 10.0× | H20: $500M | I20: Multi-chain live; $500M AUM
A21: Comparable | B21: 300000000 | C21: 0.3 | D21: ~$21M circ | E21: 75 | F21: 0.3 | G21: 20.0× | H21: $1B | I21: NXM-scale; $1B AUM; P/S ~5×
A22: Institutional | B22: 750000000 | C22: 0.75 | D22: ~$52M circ | E22: 62.5 | F22: 0.25 | G22: 50.0× | H22: $3B | I22: $3B AUM; exchange-native product
A23: Category winner | B23: 1500000000 | C23: 1.5 | D23: ~$104M circ | E23: 53.6 | F23: 0.214 | G23: 100.0× | H23: $7B+ | I23: Dominant cross-chain insurance protocol
A25: * Circulating market cap at each stage based on vesting schedule. † Implied AUM = minimum AUM required for comparable P/S multiple (using ~0.4%/yr revenue rate).
A27: C. Seed Investor Return Bridge — $1.5M at $15M FDV
A28: Exit FDV | B28: Token Price | C28: Gross Return | D28: Net MoM | E28: Approx. Year | F28: Required AUM | G28: Key Condition
A29: 30000000 | B29: 0.03 | C29: 3000000 | D29: 2.0× | E29: Y1 | F29: $100M | G29: First exchange partnership live; protocol on 1 chain
A30: 75000000 | B30: 0.075 | C30: 7500000 | D30: 5.0× | E30: Y2 | F30: $250M | G30: 2 chains, 1 major exchange integration, no trigger
A31: 150000000 | B31: 0.15 | C31: 15000000 | D31: 10.0× | E31: Y2-3 | F31: $500M | G31: Protocol-market fit; recurring revenue demonstrated
A32: 300000000 | B32: 0.3 | C32: 30000000 | D32: 20.0× | E32: Y3 | F32: $1B | G32: Industry standard DeFi insurance; NXM-comparable
A33: 750000000 | B33: 0.75 | C33: 75000000 | D33: 50.0× | E33: Y4 | F33: $3B | G33: Multi-chain dominant; institutional IF stakers
A34: 1500000000 | B34: 1.5 | C34: 150000000 | D34: 100.0× | E34: Y5 | F34: $7B+ | G34: Category-defining; exchange-native cross-chain insurance

Sheet 6. Sensitivity
A1: SATOSHI STOP LOSS | Sensitivity Analysis
A2: Key variable sensitivities: APY, revenue, and IF solvency. Change blue cells to explore.
A4: A. Enrollment Premium Rate vs. AUM — Annual Staker Revenue ($)
A5: Enroll Premium \ AUM | B5: $100M | C5: $250M | D5: $500M | E5: $1B | F5: $2B | G5: $5B | H5: $10B
A6: 0.2% enrollment rate | B6: 80000 | C6: 200000 | D6: 400000 | E6: 800000 | F6: 1600000 | G6: 4000000 | H6: 8000000
A7: 0.3% enrollment rate | B7: 95000 | C7: 237500 | D7: 475000 | E7: 950000 | F7: 1900000 | G7: 4750000 | H7: 9500000
A8: 0.5% enrollment rate | B8: 125000 | C8: 312500 | D8: 625000 | E8: 1250000 | F8: 2500000 | G8: 6250000 | H8: 12500000
A9: 0.7% enrollment rate | B9: 155000 | C9: 387500 | D9: 775000 | E9: 1550000 | F9: 3100000 | G9: 7750000 | H9: 15500000
A10: 1.0% enrollment rate | B10: 200000 | C10: 500000 | D10: 1000000 | E10: 2000000 | F10: 4000000 | G10: 10000000 | H10: 20000000
A11: 1.5% enrollment rate | B11: 275000 | C11: 687500 | D11: 1375000 | E11: 2750000 | F11: 5500000 | G11: 13750000 | H11: 27500000
A13: B. Annual Trigger Probability vs. IF Staker Expected Annual Return
A14: Expected return = Cash APY − (trigger probability × staker loss rate). Shows that higher trigger probability significantly erodes net expected return.
A16: Trigger Prob. \ Cash APY | B16: 1% Cash APY | C16: 2% Cash APY | D16: 3% Cash APY | E16: 5% Cash APY | F16: Loss Rate Assumed
A17: 0.5% annual trigger prob. | B17: 0.006 | C17: 0.016 | D17: 0.026 | E17: 0.046 | F17: 80% loss rate on trigger
A18: 1.0% annual trigger prob. | B18: 0.002 | C18: 0.012 | D18: 0.022 | E18: 0.042 | F18: 80% loss rate on trigger
A19: 2.0% annual trigger prob. | B19: -0.006 | C19: 0.004 | D19: 0.014 | E19: 0.034 | F19: 80% loss rate on trigger
A20: 5.0% annual trigger prob. | B20: -0.03 | C20: -0.02 | D20: -0.01 | E20: 0.01 | F20: 80% loss rate on trigger
A21: 10.0% annual trigger prob. | B21: -0.07 | C21: -0.06 | D21: -0.05 | E21: -0.03 | F21: 80% loss rate on trigger
A23: Red = net negative expected return. Staking is only rational if cash APY > (trigger probability × loss rate). At 2% trigger probability and 80% loss rate, stakers need 1.6%+ cash APY. Base scenario delivers this from ~$200M AUM onwards.
A25: C. Staking Participation Rate vs. Cash APY — Base Scenario Year 3 ($1B AUM)
A26: Staking Participation | B26: Staked Tokens | C26: Staked USD Value | D26: Total Rev. to Stakers | E26: Cash APY | F26: Notes
A27: 20% participation | B27: 139000000 | C27: 55600000 | D27: 2415000 | E27: 0.043435252 | F27: Higher APY; fewer stakers competing
A28: 30% participation | B28: 208500000 | C28: 83400000 | D28: 2415000 | E28: 0.028956835 | F28: Higher APY; fewer stakers competing
A29: 40% participation | B29: 278000000 | C29: 111200000 | D29: 2415000 | E29: 0.021717626 | F29: Higher APY; fewer stakers competing
A30: 50% participation | B30: 347500000 | C30: 139000000 | D30: 2415000 | E30: 0.017374101 | F30: Lower APY; more stakers competing for same revenue
A31: 60% participation | B31: 417000000 | C31: 166800000 | D31: 2415000 | E31: 0.014478417 | F31: Lower APY; more stakers competing for same revenue
A32: 70% participation | B32: 486500000 | C32: 194600000 | D32: 2415000 | E32: 0.012410072 | F32: Lower APY; more stakers competing for same revenue
